{
  "poziom1": [
    {
      "id": 0,
      "pytanie": "What does 'JS' stand for?",
      "odpowiedz1": "JavaSource",
      "odpowiedz2": "JavaScript",
      "odpowiedz3": "JustScript",
      "odpowiedz4": "JsonScript",
      "prawidlowa_odpowiedz": 2
    },
    {
      "id": 1,
      "pytanie": "Which of the following is NOT a data type in JavaScript?",
      "odpowiedz1": "Number",
      "odpowiedz2": "String",
      "odpowiedz3": "Character",
      "odpowiedz4": "Boolean",
      "prawidlowa_odpowiedz": 3
    },
    {
      "id": 2,
      "pytanie": "How do you declare a variable that can change its value?",
      "odpowiedz1": "const",
      "odpowiedz2": "let",
      "odpowiedz3": "static",
      "odpowiedz4": "var",
      "prawidlowa_odpowiedz": 2
    },
    {
      "id": 3,
      "pytanie": "What will the expression typeof null return?",
      "odpowiedz1": "null",
      "odpowiedz2": "undefined",
      "odpowiedz3": "object",
      "odpowiedz4": "string",
      "prawidlowa_odpowiedz": 3
    },
    {
      "id": 4,
      "pytanie": "Which of the following will display an alert in the browser?",
      "odpowiedz1": "alert('Hello!')",
      "odpowiedz2": "console.log('Hello!')",
      "odpowiedz3": "prompt('Hello!')",
      "odpowiedz4": "confirm('Hello!')",
      "prawidlowa_odpowiedz": 1
    },
    {
      "id": 5,
      "pytanie": "Which method adds an element to the end of an array?",
      "odpowiedz1": "push()",
      "odpowiedz2": "pop()",
      "odpowiedz3": "shift()",
      "odpowiedz4": "unshift()",
      "prawidlowa_odpowiedz": 1
    },
    {
      "id": 6,
      "pytanie": "What will be the result of the expression: 2 + '2'?",
      "odpowiedz1": "4",
      "odpowiedz2": "'4'",
      "odpowiedz3": "'22'",
      "odpowiedz4": "NaN",
      "prawidlowa_odpowiedz": 3
    },
    {
      "id": 7,
      "pytanie": "How do you write an arrow function that returns the sum of two numbers?",
      "odpowiedz1": "function sum(a,b) { return a+b; }",
      "odpowiedz2": "(a,b) => { return a+b; }",
      "odpowiedz3": "(a,b) -> a+b",
      "odpowiedz4": "(a,b): a+b",
      "prawidlowa_odpowiedz": 2
    },
    {
      "id": 8,
      "pytanie": "What boolean value will Boolean(0) return?",
      "odpowiedz1": "true",
      "odpowiedz2": "false",
      "odpowiedz3": "undefined",
      "odpowiedz4": "null",
      "prawidlowa_odpowiedz": 2
    },
    {
      "id": 9,
      "pytanie": "Which statement about '===' is true?",
      "odpowiedz1": "It compares only values",
      "odpowiedz2": "It compares both value and type",
      "odpowiedz3": "It always returns false",
      "odpowiedz4": "It works only for numbers",
      "prawidlowa_odpowiedz": 2
    },
    {
      "id": 10,
      "pytanie": "Which keyword is used to create a class in JavaScript?",
      "odpowiedz1": "object",
      "odpowiedz2": "function",
      "odpowiedz3": "class",
      "odpowiedz4": "struct",
      "prawidlowa_odpowiedz": 3
    }
  ],
  "poziom1b": [
    {
      "id": 0,
      "pytanie": "What does 'JS' stand for?",
      "odpowiedz1": "JavaSource",
      "odpowiedz2": "JavaScript",
      "odpowiedz3": "JustScript",
      "odpowiedz4": "JsonScript",
      "prawidlowa_odpowiedz": 2
    },
    {
      "id": 1,
      "pytanie": "Which of the following is NOT a data type in JavaScript?",
      "odpowiedz1": "Number",
      "odpowiedz2": "String",
      "odpowiedz3": "Character",
      "odpowiedz4": "Boolean",
      "prawidlowa_odpowiedz": 3
    },
    {
      "id": 2,
      "pytanie": "How do you declare a variable that can change its value?",
      "odpowiedz1": "const",
      "odpowiedz2": "let",
      "odpowiedz3": "static",
      "odpowiedz4": "var",
      "prawidlowa_odpowiedz": 2
    },
    {
      "id": 3,
      "pytanie": "What will the expression typeof null return?",
      "odpowiedz1": "null",
      "odpowiedz2": "undefined",
      "odpowiedz3": "object",
      "odpowiedz4": "string",
      "prawidlowa_odpowiedz": 3
    },
    {
      "id": 4,
      "pytanie": "Which of the following will display an alert in the browser?",
      "odpowiedz1": "alert('Hello!')",
      "odpowiedz2": "console.log('Hello!')",
      "odpowiedz3": "prompt('Hello!')",
      "odpowiedz4": "confirm('Hello!')",
      "prawidlowa_odpowiedz": 1
    },
    {
      "id": 5,
      "pytanie": "Which method adds an element to the end of an array?",
      "odpowiedz1": "push()",
      "odpowiedz2": "pop()",
      "odpowiedz3": "shift()",
      "odpowiedz4": "unshift()",
      "prawidlowa_odpowiedz": 1
    },
    {
      "id": 6,
      "pytanie": "What will be the result of the expression: 2 + '2'?",
      "odpowiedz1": "4",
      "odpowiedz2": "'4'",
      "odpowiedz3": "'22'",
      "odpowiedz4": "NaN",
      "prawidlowa_odpowiedz": 3
    },
    {
      "id": 7,
      "pytanie": "How do you write an arrow function that returns the sum of two numbers?",
      "odpowiedz1": "function sum(a,b) { return a+b; }",
      "odpowiedz2": "(a,b) => { return a+b; }",
      "odpowiedz3": "(a,b) -> a+b",
      "odpowiedz4": "(a,b): a+b",
      "prawidlowa_odpowiedz": 2
    },
    {
      "id": 8,
      "pytanie": "What boolean value will Boolean(0) return?",
      "odpowiedz1": "true",
      "odpowiedz2": "false",
      "odpowiedz3": "undefined",
      "odpowiedz4": "null",
      "prawidlowa_odpowiedz": 2
    },
    {
      "id": 9,
      "pytanie": "Which statement about '===' is true?",
      "odpowiedz1": "It compares only values",
      "odpowiedz2": "It compares both value and type",
      "odpowiedz3": "It always returns false",
      "odpowiedz4": "It works only for numbers",
      "prawidlowa_odpowiedz": 2
    },
    {
      "id": 10,
      "pytanie": "Which keyword is used to create a class in JavaScript?",
      "odpowiedz1": "object",
      "odpowiedz2": "function",
      "odpowiedz3": "class",
      "odpowiedz4": "struct",
      "prawidlowa_odpowiedz": 3
    }
  ],
  "poziom1c": [
    {
      "id": 1,
      "pytanie": "Gdzie rozgrywa się akcja noweli „Latarnik”?",
      "odpowiedz1": "Lwów",
      "odpowiedz2": "Nowy Jork",
      "odpowiedz3": "Buenos Aires",
      "odpowiedz4": "Aspinwall",
      "prawidlowa_odpowiedz": 4
    },
    {
      "id": 2,
      "pytanie": "Jak nazywa się główny bohater noweli?",
      "odpowiedz1": "Santiago",
      "odpowiedz2": "Starski",
      "odpowiedz3": "Skawiński",
      "odpowiedz4": "Sienkiewicz",
      "prawidlowa_odpowiedz": 3
    },
    {
      "id": 3,
      "pytanie": "Kim był Skawiński w Aspinwall?",
      "odpowiedz1": "księgarzem",
      "odpowiedz2": "żołnierzem",
      "odpowiedz3": "lekarzem",
      "odpowiedz4": "latarnikiem",
      "prawidlowa_odpowiedz": 4
    },
    {
      "id": 4,
      "pytanie": "Z jakiego kraju pochodzi Skawiński?",
      "odpowiedz1": "Polska",
      "odpowiedz2": "Francja",
      "odpowiedz3": "Węgry",
      "odpowiedz4": "Brazylia",
      "prawidlowa_odpowiedz": 1
    },
    {
      "id": 5,
      "pytanie": "Jaki utwór wzbudził silne emocje w bohaterze?",
      "odpowiedz1": "„Trylogia”",
      "odpowiedz2": "„Pan Tadeusz”",
      "odpowiedz3": "„Mitologia”",
      "odpowiedz4": "„Dziady”",
      "prawidlowa_odpowiedz": 2
    },
    {
      "id": 6,
      "pytanie": "Gdzie walczył Skawiński?",
      "odpowiedz1": "w Holandii, we Francji,na <br>Węgrzech i w Anglii",
      "odpowiedz2": "w Hiszpanii, we Włoszech, na <br>Węgrzech i w Stanach Zjednoczonych",
      "odpowiedz3": "w Hiszpanii, we Francji, na <br>Węgrzech i w Stanach Zjednoczonych",
      "odpowiedz4": "w Hiszpanii, w Niemczech, na <br>Węgrzech i w Stanach Zjednoczonych",
      "prawidlowa_odpowiedz": 3
    },
    {
      "id": 7,
      "pytanie": "„Latarnik” to:",
      "odpowiedz1": "nowela",
      "odpowiedz2": "dramat",
      "odpowiedz3": "powieść",
      "odpowiedz4": "bajka",
      "prawidlowa_odpowiedz": 1
    },
    {
      "id": 8,
      "pytanie": "Jak długo Skawiński był latarnikiem, zanim stracił pracę?",
      "odpowiedz1": "kilka lat",
      "odpowiedz2": "miesiąc",
      "odpowiedz3": "dwa dni",
      "odpowiedz4": "prawie rok",
      "prawidlowa_odpowiedz": 4
    },
    {
      "id": 9,
      "pytanie": "Jakie codzienne obowiązki miał Skawiński?",
      "odpowiedz1": "gotował obiad dla innych latarników",
      "odpowiedz2": "nie musiał nic robić",
      "odpowiedz3": "sprzątał latarnię morską",
      "odpowiedz4": "zapalał i gasił latarnię",
      "prawidlowa_odpowiedz": 4
    },
    {
      "id": 10,
      "pytanie": "Ile lat miał Skawiński, gdy został latarnikiem?",
      "odpowiedz1": "około 60",
      "odpowiedz2": "około 70",
      "odpowiedz3": "około 40",
      "odpowiedz4": "około 50",
      "prawidlowa_odpowiedz": 2
    }
  ]
}
